{
    "accounts": [
        {
            "id": "7Ra3rtuRbG8wnSazX0_WsQ",
            "iban": "TR450013400000020548700081",
            "availableBalance": 0.00,
            "balance": 0.00,
            "name": "MASKINGOD MASKINGN MASKINGYD",
            "number": "4540-205487-351",
            "formattedNumber": "4540 - 205487 - 351",
            "type": "VDSZMVD",
            "currencyCode": "TRY",
            "maturityDate": null,
            "maturityAmount": 0.0,
            "branchName": "",
            "isAutoInvestment": false,
            "remainingDay": 0,
            "originalProductType": "None",
            "originalProductCode": "VDSZMVD",
            "projectCode": ""
        },
        {
            "id": "C9sswO8wkJ78qzSRe52zWw",
            "iban": "TR540013400000020548700016",
            "availableBalance": -55.25,
            "balance": -55.25,
            "name": "MASKINGOD MASKINGN MASKINGYD",
            "number": "9142-205487-1",
            "formattedNumber": "9142 - 205487 - 1",
            "type": "KRDLMEV",
            "currencyCode": "TRY",
            "maturityDate": null,
            "maturityAmount": 0.0,
            "branchName": "ZİNCİRLİKUYU",
            "isAutoInvestment": false,
            "remainingDay": 0,
            "originalProductType": "None",
            "originalProductCode": "KRDLMEV",
            "projectCode": "NAKIT"
        },
        {
            "id": "We9sJXr-IRu4Mk2FSGbcSA",
            "iban": "TR270013400000020548700017",
            "availableBalance": 1050.00,
            "balance": 1050.00,
            "name": "MASKINGOD MASKINGN MASKINGYD",
            "number": "9142-205487-2",
            "formattedNumber": "9142 - 205487 - 2",
            "type": "TAHREES",
            "currencyCode": "TRY",
            "maturityDate": null,
            "maturityAmount": 0.0,
            "branchName": "ZİNCİRLİKUYU",
            "isAutoInvestment": false,
            "remainingDay": 0,
            "originalProductType": "None",
            "originalProductCode": "TAHREES",
            "projectCode": ""
        },
        {
            "id": "I_zrEyOlsLHX8_fYjcgFAw",
            "iban": "TR970013400000020548700018",
            "availableBalance": 1110.00,
            "balance": 1110.00,
            "name": "MASKINGOD MASKINGN MASKINGYD",
            "number": "9142-205487-3",
            "formattedNumber": "9142 - 205487 - 3",
            "type": "TAHREES",
            "currencyCode": "TRY",
            "maturityDate": null,
            "maturityAmount": 0.0,
            "branchName": "ZİNCİRLİKUYU",
            "isAutoInvestment": false,
            "remainingDay": 0,
            "originalProductType": "None",
            "originalProductCode": "TAHREES",
            "projectCode": ""
        },
        {
            "id": "CC6z0Kkx7bXZcOZi1Nb4PQ",
            "iban": "TR530013400000020548700034",
            "availableBalance": 1050.00,
            "balance": 1050.00,
            "name": "MASKINGOD MASKINGN MASKINGYD",
            "number": "9142-205487-4",
            "formattedNumber": "9142 - 205487 - 4",
            "type": "IHTKTIC",
            "currencyCode": "TRY",
            "maturityDate": null,
            "maturityAmount": 0.0,
            "branchName": "ZİNCİRLİKUYU",
            "isAutoInvestment": false,
            "remainingDay": 0,
            "originalProductType": "None",
            "originalProductCode": "IHTKTIC",
            "projectCode": "TTKREDT"
        },
        {
            "id": "HIZFcS-d_LFtxGVYpGuUdA",
            "iban": "TR260013400000020548700035",
            "availableBalance": 1050.00,
            "balance": 1050.00,
            "name": "MASKINGOD MASKINGN MASKINGYD",
            "number": "9142-205487-5",
            "formattedNumber": "9142 - 205487 - 5",
            "type": "TAHREES",
            "currencyCode": "TRY",
            "maturityDate": null,
            "maturityAmount": 0.0,
            "branchName": "ZİNCİRLİKUYU",
            "isAutoInvestment": false,
            "remainingDay": 0,
            "originalProductType": "None",
            "originalProductCode": "TAHREES",
            "projectCode": "TTKREDT"
        },
        {
            "id": "zYw79TU5WMib9ssE92kWlQ",
            "iban": "TR960013400000020548700036",
            "availableBalance": 1050.00,
            "balance": 1050.00,
            "name": "MASKINGOD MASKINGN MASKINGYD",
            "number": "9142-205487-6",
            "formattedNumber": "9142 - 205487 - 6",
            "type": "TAHREES",
            "currencyCode": "TRY",
            "maturityDate": null,
            "maturityAmount": 0.0,
            "branchName": "ZİNCİRLİKUYU",
            "isAutoInvestment": false,
            "remainingDay": 0,
            "originalProductType": "None",
            "originalProductCode": "TAHREES",
            "projectCode": "TTKREDT"
        },
        {
            "id": "CgRgWMKlKfRhMToztu_sYw",
            "iban": "TR420013400000020548700038",
            "availableBalance": 1050.00,
            "balance": 1050.00,
            "name": "MASKINGOD MASKINGN MASKINGYD",
            "number": "9142-205487-7",
            "formattedNumber": "9142 - 205487 - 7",
            "type": "IHTKTIC",
            "currencyCode": "TRY",
            "maturityDate": null,
            "maturityAmount": 0.0,
            "branchName": "ZİNCİRLİKUYU",
            "isAutoInvestment": false,
            "remainingDay": 0,
            "originalProductType": "None",
            "originalProductCode": "IHTKTIC",
            "projectCode": "TTKREDT"
        },
        {
            "id": "gPWkiObQnMSLOWHlI9cspQ",
            "iban": "TR150013400000020548700039",
            "availableBalance": 1050.00,
            "balance": 1050.00,
            "name": "MASKINGOD MASKINGN MASKINGYD",
            "number": "9142-205487-8",
            "formattedNumber": "9142 - 205487 - 8",
            "type": "TAHREES",
            "currencyCode": "TRY",
            "maturityDate": null,
            "maturityAmount": 0.0,
            "branchName": "ZİNCİRLİKUYU",
            "isAutoInvestment": false,
            "remainingDay": 0,
            "originalProductType": "None",
            "originalProductCode": "TAHREES",
            "projectCode": "TTKREDT"
        },
        {
            "id": "R2yOG9tELc-9B51ILhryGw",
            "iban": "TR850013400000020548700040",
            "availableBalance": 1050.00,
            "balance": 1050.00,
            "name": "MASKINGOD MASKINGN MASKINGYD",
            "number": "9142-205487-9",
            "formattedNumber": "9142 - 205487 - 9",
            "type": "TAHREES",
            "currencyCode": "TRY",
            "maturityDate": null,
            "maturityAmount": 0.0,
            "branchName": "ZİNCİRLİKUYU",
            "isAutoInvestment": false,
            "remainingDay": 0,
            "originalProductType": "None",
            "originalProductCode": "TAHREES",
            "projectCode": "TTKREDT"
        },
        {
            "id": "y0uOORahQCGbXEvugy8LJw",
            "iban": "TR580013400000020548700041",
            "availableBalance": 1050.00,
            "balance": 1050.00,
            "name": "MASKINGOD MASKINGN MASKINGYD",
            "number": "9142-205487-10",
            "formattedNumber": "9142 - 205487 - 10",
            "type": "IHTKTIC",
            "currencyCode": "TRY",
            "maturityDate": null,
            "maturityAmount": 0.0,
            "branchName": "ZİNCİRLİKUYU",
            "isAutoInvestment": false,
            "remainingDay": 0,
            "originalProductType": "None",
            "originalProductCode": "IHTKTIC",
            "projectCode": "TTKREDT"
        },
        {
            "id": "-A8wMNLzbdNzXJHoRE-IXw",
            "iban": "TR310013400000020548700042",
            "availableBalance": 1050.00,
            "balance": 1050.00,
            "name": "MASKINGOD MASKINGN MASKINGYD",
            "number": "9142-205487-11",
            "formattedNumber": "9142 - 205487 - 11",
            "type": "TAHREES",
            "currencyCode": "TRY",
            "maturityDate": null,
            "maturityAmount": 0.0,
            "branchName": "ZİNCİRLİKUYU",
            "isAutoInvestment": false,
            "remainingDay": 0,
            "originalProductType": "None",
            "originalProductCode": "TAHREES",
            "projectCode": "TTKREDT"
        },
        {
            "id": "zTb_to8wbDWx2s-z-J157w",
            "iban": "TR040013400000020548700043",
            "availableBalance": 1050.00,
            "balance": 1050.00,
            "name": "MASKINGOD MASKINGN MASKINGYD",
            "number": "9142-205487-12",
            "formattedNumber": "9142 - 205487 - 12",
            "type": "TAHREES",
            "currencyCode": "TRY",
            "maturityDate": null,
            "maturityAmount": 0.0,
            "branchName": "ZİNCİRLİKUYU",
            "isAutoInvestment": false,
            "remainingDay": 0,
            "originalProductType": "None",
            "originalProductCode": "TAHREES",
            "projectCode": "TTKREDT"
        },
        {
            "id": "S7j6UebdGY9zIt6SS-OAVg",
            "iban": "TR740013400000020548700044",
            "availableBalance": 1050.00,
            "balance": 1050.00,
            "name": "MASKINGOD MASKINGN MASKINGYD",
            "number": "9142-205487-13",
            "formattedNumber": "9142 - 205487 - 13",
            "type": "IHTKTIC",
            "currencyCode": "TRY",
            "maturityDate": null,
            "maturityAmount": 0.0,
            "branchName": "ZİNCİRLİKUYU",
            "isAutoInvestment": false,
            "remainingDay": 0,
            "originalProductType": "None",
            "originalProductCode": "IHTKTIC",
            "projectCode": "TTKREDT"
        },
        {
            "id": "nqkyvLtLAtpPAyI0CauEWw",
            "iban": "TR470013400000020548700045",
            "availableBalance": 1050.00,
            "balance": 1050.00,
            "name": "MASKINGOD MASKINGN MASKINGYD",
            "number": "9142-205487-14",
            "formattedNumber": "9142 - 205487 - 14",
            "type": "TAHREES",
            "currencyCode": "TRY",
            "maturityDate": null,
            "maturityAmount": 0.0,
            "branchName": "ZİNCİRLİKUYU",
            "isAutoInvestment": false,
            "remainingDay": 0,
            "originalProductType": "None",
            "originalProductCode": "TAHREES",
            "projectCode": "TTKREDT"
        },
        {
            "id": "jLXPo88eUgRAPLqEXaqRPg",
            "iban": "TR200013400000020548700046",
            "availableBalance": 1050.00,
            "balance": 1050.00,
            "name": "MASKINGOD MASKINGN MASKINGYD",
            "number": "9142-205487-15",
            "formattedNumber": "9142 - 205487 - 15",
            "type": "TAHREES",
            "currencyCode": "TRY",
            "maturityDate": null,
            "maturityAmount": 0.0,
            "branchName": "ZİNCİRLİKUYU",
            "isAutoInvestment": false,
            "remainingDay": 0,
            "originalProductType": "None",
            "originalProductCode": "TAHREES",
            "projectCode": "TTKREDT"
        },
        {
            "id": "EN6CQ_-tBryWKyxakdmaRA",
            "iban": "TR900013400000020548700047",
            "availableBalance": 1050.00,
            "balance": 1050.00,
            "name": "MASKINGOD MASKINGN MASKINGYD",
            "number": "9142-205487-16",
            "formattedNumber": "9142 - 205487 - 16",
            "type": "IHTKTIC",
            "currencyCode": "TRY",
            "maturityDate": null,
            "maturityAmount": 0.0,
            "branchName": "ZİNCİRLİKUYU",
            "isAutoInvestment": false,
            "remainingDay": 0,
            "originalProductType": "None",
            "originalProductCode": "IHTKTIC",
            "projectCode": "TTKREDT"
        },
        {
            "id": "qobohl7OIspTLxDvFmB_YQ",
            "iban": "TR630013400000020548700048",
            "availableBalance": 1050.00,
            "balance": 1050.00,
            "name": "MASKINGOD MASKINGN MASKINGYD",
            "number": "9142-205487-17",
            "formattedNumber": "9142 - 205487 - 17",
            "type": "TAHREES",
            "currencyCode": "TRY",
            "maturityDate": null,
            "maturityAmount": 0.0,
            "branchName": "ZİNCİRLİKUYU",
            "isAutoInvestment": false,
            "remainingDay": 0,
            "originalProductType": "None",
            "originalProductCode": "TAHREES",
            "projectCode": "TTKREDT"
        },
        {
            "id": "sVrRkCQJkMdlJTDryGdw2g",
            "iban": "TR360013400000020548700049",
            "availableBalance": 1050.00,
            "balance": 1050.00,
            "name": "MASKINGOD MASKINGN MASKINGYD",
            "number": "9142-205487-18",
            "formattedNumber": "9142 - 205487 - 18",
            "type": "TAHREES",
            "currencyCode": "TRY",
            "maturityDate": null,
            "maturityAmount": 0.0,
            "branchName": "ZİNCİRLİKUYU",
            "isAutoInvestment": false,
            "remainingDay": 0,
            "originalProductType": "None",
            "originalProductCode": "TAHREES",
            "projectCode": "TTKREDT"
        },
        {
            "id": "EH7g67EpB0GqyaAFEGzYBQ",
            "iban": "TR090013400000020548700050",
            "availableBalance": 1050.00,
            "balance": 1050.00,
            "name": "MASKINGOD MASKINGN MASKINGYD",
            "number": "9142-205487-19",
            "formattedNumber": "9142 - 205487 - 19",
            "type": "IHTKTIC",
            "currencyCode": "TRY",
            "maturityDate": null,
            "maturityAmount": 0.0,
            "branchName": "ZİNCİRLİKUYU",
            "isAutoInvestment": false,
            "remainingDay": 0,
            "originalProductType": "None",
            "originalProductCode": "IHTKTIC",
            "projectCode": "TTKREDT"
        },
        {
            "id": "6g2heKnZhGjbTSFBEkF3Bg",
            "iban": "TR790013400000020548700051",
            "availableBalance": 1050.00,
            "balance": 1050.00,
            "name": "MASKINGOD MASKINGN MASKINGYD",
            "number": "9142-205487-20",
            "formattedNumber": "9142 - 205487 - 20",
            "type": "TAHREES",
            "currencyCode": "TRY",
            "maturityDate": null,
            "maturityAmount": 0.0,
            "branchName": "ZİNCİRLİKUYU",
            "isAutoInvestment": false,
            "remainingDay": 0,
            "originalProductType": "None",
            "originalProductCode": "TAHREES",
            "projectCode": "TTKREDT"
        },
        {
            "id": "k-u9Z-s8g03fuxInPNVQSw",
            "iban": "TR520013400000020548700052",
            "availableBalance": 1050.00,
            "balance": 1050.00,
            "name": "MASKINGOD MASKINGN MASKINGYD",
            "number": "9142-205487-21",
            "formattedNumber": "9142 - 205487 - 21",
            "type": "TAHREES",
            "currencyCode": "TRY",
            "maturityDate": null,
            "maturityAmount": 0.0,
            "branchName": "ZİNCİRLİKUYU",
            "isAutoInvestment": false,
            "remainingDay": 0,
            "originalProductType": "None",
            "originalProductCode": "TAHREES",
            "projectCode": "TTKREDT"
        },
        {
            "id": "2TyjUD0rjcceR8zZqi9Vgw",
            "iban": "TR110013400000020548700014",
            "availableBalance": 15990324.43,
            "balance": 15991324.43,
            "name": "MASKINGOD MASKINGN MASKINGYD ",
            "number": "9142-205487-351",
            "formattedNumber": "9142 - 205487 - 351",
            "type": "VDSZMVD",
            "currencyCode": "TRY",
            "maturityDate": null,
            "maturityAmount": 0.0,
            "branchName": "ZİNCİRLİKUYU",
            "isAutoInvestment": false,
            "remainingDay": 0,
            "originalProductType": "None",
            "originalProductCode": "VDSZMVD",
            "projectCode": ""
        },
        {
            "id": "xhF0UEcMV_Pclzp8goPJ5g",
            "iban": "TR810013400000020548700015",
            "availableBalance": 4119.50,
            "balance": 2164.75,
            "name": "MASKINGOD MASKINGN MASKINGYD GÖKHAN ONUR",
            "number": "9142-205487-352",
            "formattedNumber": "9142 - 205487 - 352",
            "type": "VDSZMVD",
            "currencyCode": "TRY",
            "maturityDate": null,
            "maturityAmount": 0.0,
            "branchName": "ZİNCİRLİKUYU",
            "isAutoInvestment": false,
            "remainingDay": 0,
            "originalProductType": "None",
            "originalProductCode": "VDSZMVD",
            "projectCode": ""
        },
        {
            "id": "2YjWJBmKrOGHwNxbTwDDuQ",
            "iban": "TR160013400000020548700021",
            "availableBalance": 1050.00,
            "balance": 1050.00,
            "name": "deneme",
            "number": "9142-205487-355",
            "formattedNumber": "9142 - 205487 - 355",
            "type": "VDLMEVD",
            "currencyCode": "TRY",
            "maturityDate": "2018-10-19T0:00:00.0000000+03:00",
            "maturityAmount": 0.0,
            "branchName": "ZİNCİRLİKUYU",
            "isAutoInvestment": false,
            "remainingDay": 0,
            "originalProductType": "None",
            "originalProductCode": "VDLMEVD",
            "projectCode": "YENİV"
        },
        {
            "id": "qh5vGG-lBEqgk2d880Y7zg",
            "iban": "TR860013400000020548700022",
            "availableBalance": 1050.00,
            "balance": 1050.00,
            "name": "MASKINGOD MASKINGN MASKINGYD",
            "number": "9142-205487-356",
            "formattedNumber": "9142 - 205487 - 356",
            "type": "VDLMEVD",
            "currencyCode": "TRY",
            "maturityDate": "2018-10-19T0:00:00.0000000+03:00",
            "maturityAmount": 0.0,
            "branchName": "ZİNCİRLİKUYU",
            "isAutoInvestment": false,
            "remainingDay": 0,
            "originalProductType": "None",
            "originalProductCode": "VDLMEVD",
            "projectCode": ""
        },
        {
            "id": "oMflf6-2x8L-QCmTshBWCg",
            "iban": "TR590013400000020548700023",
            "availableBalance": 1050.00,
            "balance": 1050.00,
            "name": "MASKINGOD MASKINGN MASKINGYD",
            "number": "9142-205487-357",
            "formattedNumber": "9142 - 205487 - 357",
            "type": "VDLMEVD",
            "currencyCode": "TRY",
            "maturityDate": "2018-01-24T0:00:00.0000000+03:00",
            "maturityAmount": 0.0,
            "branchName": "ZİNCİRLİKUYU",
            "isAutoInvestment": false,
            "remainingDay": 0,
            "originalProductType": "None",
            "originalProductCode": "VDLMEVD",
            "projectCode": ""
        },
        {
            "id": "JHJ6ZTdomd0NxSSMnTTl2A",
            "iban": "TR320013400000020548700024",
            "availableBalance": 1050.00,
            "balance": 1050.00,
            "name": "MASKINGOD MASKINGN MASKINGYD",
            "number": "9142-205487-358",
            "formattedNumber": "9142 - 205487 - 358",
            "type": "VDLMEVD",
            "currencyCode": "TRY",
            "maturityDate": "2018-02-19T0:00:00.0000000+03:00",
            "maturityAmount": 0.0,
            "branchName": "ZİNCİRLİKUYU",
            "isAutoInvestment": false,
            "remainingDay": 0,
            "originalProductType": "None",
            "originalProductCode": "VDLMEVD",
            "projectCode": ""
        },
        {
            "id": "uEFliqYXSIhs1fcNEQzbRA",
            "iban": "TR050013400000020548700025",
            "availableBalance": 1050.00,
            "balance": 1050.00,
            "name": "MASKINGOD MASKINGN MASKINGYD",
            "number": "9142-205487-359",
            "formattedNumber": "9142 - 205487 - 359",
            "type": "VDLMEVD",
            "currencyCode": "TRY",
            "maturityDate": "2018-02-19T0:00:00.0000000+03:00",
            "maturityAmount": 0.0,
            "branchName": "ZİNCİRLİKUYU",
            "isAutoInvestment": false,
            "remainingDay": 0,
            "originalProductType": "None",
            "originalProductCode": "VDLMEVD",
            "projectCode": ""
        },
        {
            "id": "CeG8CW-8IDvIUf0rBzmx4A",
            "iban": "TR750013400000020548700026",
            "availableBalance": 1050.00,
            "balance": 1050.00,
            "name": "MASKINGOD MASKINGN MASKINGYD",
            "number": "9142-205487-360",
            "formattedNumber": "9142 - 205487 - 360",
            "type": "VDLMEVD",
            "currencyCode": "TRY",
            "maturityDate": "2018-02-16T0:00:00.0000000+03:00",
            "maturityAmount": 0.0,
            "branchName": "ZİNCİRLİKUYU",
            "isAutoInvestment": false,
            "remainingDay": 0,
            "originalProductType": "None",
            "originalProductCode": "VDLMEVD",
            "projectCode": ""
        },
        {
            "id": "0a2Gi1FvQmwyTy6ZN6wzig",
            "iban": "TR480013400000020548700027",
            "availableBalance": 1050.00,
            "balance": 1050.00,
            "name": "MASKINGOD MASKINGN MASKINGYD",
            "number": "9142-205487-361",
            "formattedNumber": "9142 - 205487 - 361",
            "type": "VDLARDM",
            "currencyCode": "TRY",
            "maturityDate": "2019-02-01T0:00:00.0000000+03:00",
            "maturityAmount": 0.0,
            "branchName": "ZİNCİRLİKUYU",
            "isAutoInvestment": false,
            "remainingDay": 8,
            "originalProductType": "None",
            "originalProductCode": "VDLARDM",
            "projectCode": "VDLADFO"
        },
        {
            "id": "wjUh2tqg9rOl25Ze3kUL3A",
            "iban": "TR680013400000020548700055",
            "availableBalance": 1050.00,
            "balance": 1050.00,
            "name": "ddd",
            "number": "9142-205487-369",
            "formattedNumber": "9142 - 205487 - 369",
            "type": "VDLMEVD",
            "currencyCode": "TRY",
            "maturityDate": "2018-03-09T0:00:00.0000000+03:00",
            "maturityAmount": 0.0,
            "branchName": "ZİNCİRLİKUYU",
            "isAutoInvestment": false,
            "remainingDay": 0,
            "originalProductType": "Deniz",
            "originalProductCode": "VDLMEVD",
            "projectCode": "VDLOVRN"
        },
        {
            "id": "GYGdXHc3rGVzLTvvdZmV5g",
            "iban": "TR140013400000020548700057",
            "availableBalance": 1050.00,
            "balance": 1050.00,
            "name": "Vadeli TL Hesabım",
            "number": "9142-205487-371",
            "formattedNumber": "9142 - 205487 - 371",
            "type": "VDLMEVD",
            "currencyCode": "TRY",
            "maturityDate": "2018-08-27T0:00:00.0000000+03:00",
            "maturityAmount": 0.0,
            "branchName": "ZİNCİRLİKUYU",
            "isAutoInvestment": false,
            "remainingDay": 0,
            "originalProductType": "None",
            "originalProductCode": "VDLMEVD",
            "projectCode": "PRSONEL"
        },
        {
            "id": "270u5LEzL8H0M9TNRFBbNA",
            "iban": "TR840013400000020548700058",
            "availableBalance": 1050.00,
            "balance": 1050.00,
            "name": "Vadeli TL Hesabım",
            "number": "9142-205487-372",
            "formattedNumber": "9142 - 205487 - 372",
            "type": "VDLMEVD",
            "currencyCode": "TRY",
            "maturityDate": "2018-08-27T0:00:00.0000000+03:00",
            "maturityAmount": 0.0,
            "branchName": "ZİNCİRLİKUYU",
            "isAutoInvestment": false,
            "remainingDay": 0,
            "originalProductType": "None",
            "originalProductCode": "VDLMEVD",
            "projectCode": "PRSONEL"
        },
        {
            "id": "Hgt-KTKu5z8My27hw-3dCw",
            "iban": "TR890013400000020548700065",
            "availableBalance": 1050.00,
            "balance": 1050.00,
            "name": "MASKINGOD MASKINGN MASKINGYD",
            "number": "9142-205487-379",
            "formattedNumber": "9142 - 205487 - 379",
            "type": "BRKMEVD",
            "currencyCode": "TRY",
            "maturityDate": "2021-10-11T0:00:00.0000000+03:00",
            "maturityAmount": 0.0,
            "branchName": "ZİNCİRLİKUYU",
            "isAutoInvestment": false,
            "remainingDay": 991,
            "originalProductType": "None",
            "originalProductCode": "BRKMEVD",
            "projectCode": ""
        },
        {
            "id": "QVFLiZnXBhyQN-Kj1l3tDg",
            "iban": "TR620013400000020548700066",
            "availableBalance": 1035.58,
            "balance": 1035.58,
            "name": "seda test ",
            "number": "9142-205487-380",
            "formattedNumber": "9142 - 205487 - 380",
            "type": "VDSZMVD",
            "currencyCode": "TRY",
            "maturityDate": null,
            "maturityAmount": 0.0,
            "branchName": "ZİNCİRLİKUYU",
            "isAutoInvestment": false,
            "remainingDay": 0,
            "originalProductType": "None",
            "originalProductCode": "VDSZMVD",
            "projectCode": ""
        },
        {
            "id": "b5tnUIQ5cOKSO3akn7S9iQ",
            "iban": "TR940013400000020548700072",
            "availableBalance": 1050.00,
            "balance": 1050.00,
            "name": "Vadeli TL Hesabım",
            "number": "9142-205487-386",
            "formattedNumber": "9142 - 205487 - 386",
            "type": "VDLMEVD",
            "currencyCode": "TRY",
            "maturityDate": "2018-12-13T0:00:00.0000000+03:00",
            "maturityAmount": 0.0,
            "branchName": "ZİNCİRLİKUYU",
            "isAutoInvestment": false,
            "remainingDay": 0,
            "originalProductType": "None",
            "originalProductCode": "VDLMEVD",
            "projectCode": ""
        },
        {
            "id": "i9ceZ57G0Fi_eDRzHKeCNw",
            "iban": "TR670013400000020548700073",
            "availableBalance": 1550.00,
            "balance": 1550.00,
            "name": "Vadeli TL Hesabım",
            "number": "9142-205487-387",
            "formattedNumber": "9142 - 205487 - 387",
            "type": "VDLMEVD",
            "currencyCode": "TRY",
            "maturityDate": "2019-01-10T0:00:00.0000000+03:00",
            "maturityAmount": 0.0,
            "branchName": "ZİNCİRLİKUYU",
            "isAutoInvestment": false,
            "remainingDay": 0,
            "originalProductType": "None",
            "originalProductCode": "VDLMEVD",
            "projectCode": ""
        },
        {
            "id": "L0Cw3VS4fvKtiY-NEjqfKQ",
            "iban": "TR400013400000020548700074",
            "availableBalance": 550.00,
            "balance": 550.00,
            "name": "aaa ",
            "number": "9142-205487-388",
            "formattedNumber": "9142 - 205487 - 388",
            "type": "VDSZMVD",
            "currencyCode": "TRY",
            "maturityDate": null,
            "maturityAmount": 0.0,
            "branchName": "ZİNCİRLİKUYU",
            "isAutoInvestment": false,
            "remainingDay": 0,
            "originalProductType": "None",
            "originalProductCode": "VDSZMVD",
            "projectCode": ""
        },
        {
            "id": "EItWdlNb20Mlto8f-p4cDg",
            "iban": "TR130013400000020548700075",
            "availableBalance": 2050.00,
            "balance": 2050.00,
            "name": "Vadeli TL Hesabım",
            "number": "9142-205487-389",
            "formattedNumber": "9142 - 205487 - 389",
            "type": "VDLMEVD",
            "currencyCode": "TRY",
            "maturityDate": "2019-01-10T0:00:00.0000000+03:00",
            "maturityAmount": 0.0,
            "branchName": "ZİNCİRLİKUYU",
            "isAutoInvestment": false,
            "remainingDay": 0,
            "originalProductType": "None",
            "originalProductCode": "VDLMEVD",
            "projectCode": ""
        },
        {
            "id": "wdhkAwUgroDfPVwP1Iomfg",
            "iban": "TR830013400000020548700076",
            "availableBalance": 50.00,
            "balance": 50.00,
            "name": "sdsds ",
            "number": "9142-205487-390",
            "formattedNumber": "9142 - 205487 - 390",
            "type": "VDSZMVD",
            "currencyCode": "TRY",
            "maturityDate": null,
            "maturityAmount": 0.0,
            "branchName": "ZİNCİRLİKUYU",
            "isAutoInvestment": false,
            "remainingDay": 0,
            "originalProductType": "None",
            "originalProductCode": "VDSZMVD",
            "projectCode": ""
        },
        {
            "id": "sstSLSL-uu0j1OOVZRO6sw",
            "iban": "TR560013400000020548700077",
            "availableBalance": 250.00,
            "balance": 250.00,
            "name": "aradonem",
            "number": "9142-205487-391",
            "formattedNumber": "9142 - 205487 - 391",
            "type": "VDLARDM",
            "currencyCode": "TRY",
            "maturityDate": "2020-01-06T0:00:00.0000000+03:00",
            "maturityAmount": 0.0,
            "branchName": "ZİNCİRLİKUYU",
            "isAutoInvestment": false,
            "remainingDay": 347,
            "originalProductType": "None",
            "originalProductCode": "VDLARDM",
            "projectCode": "VDLADFO"
        },
        {
            "id": "KvfunhoywzwXkSpRL1G0tw",
            "iban": "TR290013400000020548700078",
            "availableBalance": 0.00,
            "balance": 0.00,
            "name": "aradonem 3000tl",
            "number": "9142-205487-392",
            "formattedNumber": "9142 - 205487 - 392",
            "type": "VDLARDM",
            "currencyCode": "TRY",
            "maturityDate": "2020-01-06T0:00:00.0000000+03:00",
            "maturityAmount": 0.0,
            "branchName": "ZİNCİRLİKUYU",
            "isAutoInvestment": false,
            "remainingDay": 347,
            "originalProductType": "None",
            "originalProductCode": "VDLARDM",
            "projectCode": "VDLADFO"
        },
        {
            "id": "Ujdtt3WkeXW0EOpoUOcOng",
            "iban": "TR720013400000020548700080",
            "availableBalance": 500.00,
            "balance": 500.00,
            "name": "500",
            "number": "9142-205487-394",
            "formattedNumber": "9142 - 205487 - 394",
            "type": "VDLMEVD",
            "currencyCode": "TRY",
            "maturityDate": "2019-04-16T0:00:00.0000000+03:00",
            "maturityAmount": 0.0,
            "branchName": "ZİNCİRLİKUYU",
            "isAutoInvestment": false,
            "remainingDay": 82,
            "originalProductType": "None",
            "originalProductCode": "VDLMEVD",
            "projectCode": ""
        },
        {
            "id": "FB5cRDzgHpWm6sVX7izjug",
            "iban": "TR370013400000020548700031",
            "availableBalance": 14997855.25,
            "balance": 14997855.25,
            "name": "MASKINGOD MASKINGN MASKINGYD",
            "number": "9300-205487-354",
            "formattedNumber": "9300 - 205487 - 354",
            "type": "VDSZYTR",
            "currencyCode": "TRY",
            "maturityDate": null,
            "maturityAmount": 0.0,
            "branchName": "INTERNET SUBESİ",
            "isAutoInvestment": false,
            "remainingDay": 0,
            "originalProductType": "Yatirim",
            "originalProductCode": "VDSZMVD",
            "projectCode": "VDSZYTR"
        },
        {
            "id": "1d8LXnnXXHMJUkeFYkGh_w",
            "iban": "TR430013400000020548700020",
            "availableBalance": -2461.40,
            "balance": 1050.00,
            "name": "USD ",
            "number": "9142-205487-354",
            "formattedNumber": "9142 - 205487 - 354",
            "type": "VDSZMVD",
            "currencyCode": "USD",
            "maturityDate": null,
            "maturityAmount": 0.0,
            "branchName": "ZİNCİRLİKUYU",
            "isAutoInvestment": false,
            "remainingDay": 0,
            "originalProductType": "None",
            "originalProductCode": "VDSZMVD",
            "projectCode": ""
        },
        {
            "id": "t0SdGxadVuy72e1XxTzPTg",
            "iban": "TR590012300000020548700053",
            "availableBalance": 1050.00,
            "balance": 1050.00,
            "name": "MASKINGOD MASKINGN MASKINGYD",
            "number": "9142-205487-367",
            "formattedNumber": "9142 - 205487 - 367",
            "type": "VDLMEVD",
            "currencyCode": "USD",
            "maturityDate": "2018-10-24T0:00:00.0000000+03:00",
            "maturityAmount": 0.0,
            "branchName": "ZİNCİRLİKUYU",
            "isAutoInvestment": false,
            "remainingDay": 0,
            "originalProductType": "None",
            "originalProductCode": "VDLMEVD",
            "projectCode": "VDLMDRN"
        },
        {
            "id": "IR4RkbTKERv9YnpjTjvAPA",
            "iban": "TR690013400000020548700037",
            "availableBalance": 1050.00,
            "balance": 1050.00,
            "name": "TEST2 ",
            "number": "9142-205487-366",
            "formattedNumber": "9142 - 205487 - 366",
            "type": "VDSZMVD",
            "currencyCode": "EUR",
            "maturityDate": null,
            "maturityAmount": 0.0,
            "branchName": "ZİNCİRLİKUYU",
            "isAutoInvestment": false,
            "remainingDay": 0,
            "originalProductType": "None",
            "originalProductCode": "VDSZMVD",
            "projectCode": ""
        },
        {
            "id": "IxUDhOzxUVh840JvH1eWmQ",
            "iban": "TR240013400000020548700071",
            "availableBalance": 1050.00,
            "balance": 1050.00,
            "name": "test cagri ",
            "number": "9142-205487-385",
            "formattedNumber": "9142 - 205487 - 385",
            "type": "VDSZMVD",
            "currencyCode": "GBP",
            "maturityDate": null,
            "maturityAmount": 0.0,
            "branchName": "ZİNCİRLİKUYU",
            "isAutoInvestment": false,
            "remainingDay": 0,
            "originalProductType": "None",
            "originalProductCode": "VDSZMVD",
            "projectCode": ""
        },
        {
            "id": "0Pxuu7p5wRbfnGwhC89tnA",
            "iban": "TR080013400000020548700068",
            "availableBalance": 1050.00,
            "balance": 1050.00,
            "name": "cgr ",
            "number": "9142-205487-382",
            "formattedNumber": "9142 - 205487 - 382",
            "type": "VDSZMVD",
            "currencyCode": "CAD",
            "maturityDate": null,
            "maturityAmount": 0.0,
            "branchName": "ZİNCİRLİKUYU",
            "isAutoInvestment": false,
            "remainingDay": 0,
            "originalProductType": "None",
            "originalProductCode": "VDSZMVD",
            "projectCode": ""
        },
        {
            "id": "8bQjqZXiHN5uP9TqAGii7Q",
            "iban": "TR440012300000020548700032",
            "availableBalance": 1050.00,
            "balance": 1050.00,
            "name": "ewdewfwe ",
            "number": "9142-205487-364",
            "formattedNumber": "9142 - 205487 - 364",
            "type": "VDSZMVD",
            "currencyCode": "XAU",
            "maturityDate": null,
            "maturityAmount": 0.0,
            "branchName": "ZİNCİRLİKUYU",
            "isAutoInvestment": false,
            "remainingDay": 0,
            "originalProductType": "None",
            "originalProductCode": "VDSZMVD",
            "projectCode": ""
        },
        {
            "id": "9FP_AtFTr86YwtXr34A_HQ",
            "iban": "TR030013400000020548700061",
            "availableBalance": 1050.00,
            "balance": 1050.00,
            "name": "MASKINGOD MASKINGN MASKINGYD",
            "number": "9142-205487-375",
            "formattedNumber": "9142 - 205487 - 375",
            "type": "BRKMEVD",
            "currencyCode": "XAU",
            "maturityDate": "2021-10-11T0:00:00.0000000+03:00",
            "maturityAmount": 0.0,
            "branchName": "ZİNCİRLİKUYU",
            "isAutoInvestment": false,
            "remainingDay": 991,
            "originalProductType": "None",
            "originalProductCode": "BRKMEVD",
            "projectCode": ""
        },
        {
            "id": "eLTgJo7MY5A0mX6JkLlR-w",
            "iban": "TR730013400000020548700062",
            "availableBalance": 1050.00,
            "balance": 1050.00,
            "name": "MASKINGOD MASKINGN MASKINGYD",
            "number": "9142-205487-376",
            "formattedNumber": "9142 - 205487 - 376",
            "type": "BRKMEVD",
            "currencyCode": "XAU",
            "maturityDate": "2021-10-11T0:00:00.0000000+03:00",
            "maturityAmount": 0.0,
            "branchName": "ZİNCİRLİKUYU",
            "isAutoInvestment": false,
            "remainingDay": 991,
            "originalProductType": "None",
            "originalProductCode": "BRKMEVD",
            "projectCode": ""
        },
        {
            "id": "wTqR3LTrkjQ10VRSlQfC5A",
            "iban": "TR460013400000020548700063",
            "availableBalance": 1050.00,
            "balance": 1050.00,
            "name": "MASKINGOD MASKINGN MASKINGYD",
            "number": "9142-205487-377",
            "formattedNumber": "9142 - 205487 - 377",
            "type": "VDLMEVD",
            "currencyCode": "XAU",
            "maturityDate": "2019-04-08T0:00:00.0000000+03:00",
            "maturityAmount": 0.0,
            "branchName": "ZİNCİRLİKUYU",
            "isAutoInvestment": false,
            "remainingDay": 74,
            "originalProductType": "None",
            "originalProductCode": "VDLMEVD",
            "projectCode": "YENİV"
        },
        {
            "id": "ChnXad4gZGxMsPX_U7k1qA",
            "iban": "TR700013400000020548700019",
            "availableBalance": 1050.00,
            "balance": 1050.00,
            "name": "asdasda ",
            "number": "9142-205487-353",
            "formattedNumber": "9142 - 205487 - 353",
            "type": "VDSZMVD",
            "currencyCode": "XAG",
            "maturityDate": null,
            "maturityAmount": 0.0,
            "branchName": "ZİNCİRLİKUYU",
            "isAutoInvestment": false,
            "remainingDay": 0,
            "originalProductType": "None",
            "originalProductCode": "VDSZMVD",
            "projectCode": ""
        }
    ]
}